EasyClean/EasyClean.py
EasyClean/__init__.py
EasyClean/modules.py
py_EasyClean-1.1.1.dist-info/LICENSE.txt
py_EasyClean-1.1.1.dist-info/METADATA
py_EasyClean-1.1.1.dist-info/WHEEL
py_EasyClean-1.1.1.dist-info/top_level.txt
py_EasyClean-1.1.1.dist-info/RECORD
