Metadata-Version: 2.1
Name: py-EasyClean
Version: 1.1.1
Summary: EasyClean - Automated Data Preprocessing & Cleaning using python
Home-page: https://github.com/Junaidd-Ahmedd109/EasyClean
Author: Junaid Ahmed
Author-email: ahmedjunaid109@gmail.com
Keywords: automated,cleaning,preprocessing,Easyclean
Classifier: Development Status :: 5 - Production/Stable
Classifier: Intended Audience :: Developers
Classifier: Topic :: Software Development :: Build Tools
Classifier: Programming Language :: Python :: 3.7
Classifier: Programming Language :: Python :: 3.8
Classifier: Programming Language :: Python :: 3.9
License-File: LICENSE.txt
Requires-Dist: scikit-learn
Requires-Dist: numpy
Requires-Dist: pandas
Requires-Dist: loguru
